bay_wheels/__init__.py
bay_wheels/auth.py
bay_wheels/client.py
bay_wheels/exceptions.py
bay_wheels/models.py
bay_wheels/py.typed
bay_wheels-0.3.0.dist-info/METADATA
bay_wheels-0.3.0.dist-info/WHEEL
bay_wheels-0.3.0.dist-info/RECORD
