Metadata-Version: 2.4
Name: bay-wheels
Version: 0.3.0
Summary: Unofficial Python client for the Bay Wheels bike-share API
Project-URL: Homepage, https://github.com/codetheweb/bay-wheels-py
Project-URL: Repository, https://github.com/codetheweb/bay-wheels-py
Project-URL: Issues, https://github.com/codetheweb/bay-wheels-py/issues
Author-email: Max Isom <hi@maxisom.me>
License-Expression: MIT
Keywords: api,async,bay-wheels,bike-share,bikeshare,lyft
Classifier: Development Status :: 4 - Beta
Classifier: Intended Audience :: Developers
Classifier: License :: OSI Approved :: MIT License
Classifier: Programming Language :: Python :: 3
Classifier: Programming Language :: Python :: 3.10
Classifier: Programming Language :: Python :: 3.11
Classifier: Programming Language :: Python :: 3.12
Classifier: Programming Language :: Python :: 3.13
Classifier: Typing :: Typed
Requires-Python: >=3.10
Requires-Dist: curl-cffi>=0.6.0
Requires-Dist: pydantic>=2.0.0
